pdoc/__init__.py
pdoc/__main__.py
pdoc/_version.py
pdoc/build-index.js
pdoc/cli.py
pdoc/doc.py
pdoc/documentation.md
pdoc/extract.py
pdoc/html_helpers.py
pdoc/package.json
pdoc/render.py
pdoc/static.py
pdoc/version.py
pdoc/web.py
pdoc/templates/LICENSE
pdoc/templates/README.md
pdoc/templates/_lunr_search.inc.mako
pdoc/templates/config.mako
pdoc/templates/credits.mako
pdoc/templates/css.mako
pdoc/templates/head.mako
pdoc/templates/html.mako
pdoc/templates/html_frame.mako
pdoc/templates/html_index.mako
pdoc/templates/html_module.mako
pdoc/templates/logo.mako
pdoc/templates/pdf.mako
pdoc/templates/search.mako
pdoc/templates/text.mako
pdoc/test/__init__.py
pdoc/test/__main__.py
pdoc/test/css.mako
pdoc/test/html.mako
pdoc/test/example_pkg/__init__.py
pdoc/test/example_pkg/_imported_once.py
pdoc/test/example_pkg/index.py
pdoc/test/example_pkg/module.py
pdoc/test/example_pkg/_exclude_dir/__init__.py
pdoc/test/example_pkg/_exclude_dir/downloaded_modules/foo.py
pdoc/test/example_pkg/_namespace/1/a/a/util.py
pdoc/test/example_pkg/_namespace/1/b/a/main.py
pdoc/test/example_pkg/_namespace/2/a/a/__init__.py
pdoc/test/example_pkg/_namespace/2/a/a/util.py
pdoc/test/example_pkg/_namespace/2/b/a/__init__.py
pdoc/test/example_pkg/_namespace/2/b/a/main.py
pdoc/test/example_pkg/_namespace/3/a/a/__init__.py
pdoc/test/example_pkg/_namespace/3/a/a/util.py
pdoc/test/example_pkg/_namespace/3/b/a/__init__.py
pdoc/test/example_pkg/_namespace/3/b/a/main.py
pdoc/test/example_pkg/_private/__init__.py
pdoc/test/example_pkg/_private/_private.py
pdoc/test/example_pkg/_private/module.py
pdoc/test/example_pkg/_reST_include/_include_me.py
pdoc/test/example_pkg/_reST_include/table.md
pdoc/test/example_pkg/_reST_include/test.py
pdoc/test/example_pkg/_relative_import/__init__.py
pdoc/test/example_pkg/_relative_import/foo.py
pdoc/test/example_pkg/_resolve_typing_forwardrefs/evaluated.py
pdoc/test/example_pkg/_resolve_typing_forwardrefs/postponed.py
pdoc/test/example_pkg/_skip_errors/unimportable.py
pdoc3-0.11.6.dist-info/LICENSE.txt
pdoc3-0.11.6.dist-info/METADATA
pdoc3-0.11.6.dist-info/WHEEL
pdoc3-0.11.6.dist-info/entry_points.txt
pdoc3-0.11.6.dist-info/top_level.txt
pdoc3-0.11.6.dist-info/RECORD
