Metadata-Version: 2.1
Name: pdoc3
Version: 0.11.6
Summary: Auto-generate API documentation for Python projects.
Home-page: https://pdoc3.github.io/pdoc/
License: AGPL-3.0
Project-URL: Documentation, https://pdoc3.github.io/pdoc/doc/pdoc/
Project-URL: Source, https://github.com/pdoc3/pdoc/
Project-URL: Tracker, https://github.com/pdoc3/pdoc/issues
Classifier: Topic :: Documentation
Classifier: Topic :: Software Development :: Documentation
Classifier: Topic :: Utilities
Classifier: License :: OSI Approved :: GNU Affero General Public License v3 or later (AGPLv3+)
Classifier: Development Status :: 5 - Production/Stable
Classifier: Environment :: Console
Classifier: Intended Audience :: Developers
Classifier: Operating System :: OS Independent
Classifier: Programming Language :: Python :: 3 :: Only
Provides: pdoc
Obsoletes: pdoc
Requires-Python: >= 3.9
License-File: LICENSE.txt
Requires-Dist: mako
Requires-Dist: markdown>=3.0
